robotframework_construct/__init__.py
robotframework_construct/_reflector.py
robotframework_construct/_regmap.py
robotframework_construct-0.3.1.dist-info/METADATA
robotframework_construct-0.3.1.dist-info/WHEEL
robotframework_construct-0.3.1.dist-info/licenses/LICENSE.txt
robotframework_construct-0.3.1.dist-info/RECORD
