Metadata-Version: 2.4
Name: robotframework-construct
Version: 0.3.1
Summary: Infrastructure to use construct Structs in robotframework
Project-URL: Documentation, https://marketsquare.github.io/robotframework-construct
Project-URL: Repository, https://github.com/MarketSquare/robotframework-construct
Project-URL: Release_Notes, https://marketsquare.github.io/robotframework-construct/release_notes.md
Author-email: Franz Haas <franz.dominik.haas@gmail.com>
License-Expression: Apache-2.0
License-File: LICENSE.txt
Keywords: robotframework
Requires-Python: >=3.10.0
Requires-Dist: construct==2.10.69
Requires-Dist: robotframework>=7.1
Provides-Extra: breakout
Requires-Dist: ruamel-yaml>=0.18.6; extra == 'breakout'
Requires-Dist: xonsh>=0.18.4; extra == 'breakout'
Provides-Extra: nci
Requires-Dist: pyserial; extra == 'nci'
Provides-Extra: test
Requires-Dist: cosmic-ray>=8.3.15; extra == 'test'
Requires-Dist: pymongo>=4.9.1; extra == 'test'
Requires-Dist: pytest>=8.3.3; extra == 'test'
Requires-Dist: ruff>=0.7.2; extra == 'test'
Requires-Dist: stdf-tamer[robotframework]>=1.0.44; extra == 'test'
